{"ZNXzVSV6UdO4eq2jINtGBQ==":"skyscraper-3136593-2000x1325.jpg","HC7h7y0eWpNpMQR7AywONQ==":"pexels-photo-417411-2000x1336.jpg","fSXP8xeecqigvZpv807z2A==":"eddi-268x358.jpg","auTe4KX62/ouvbHaudS83g==":"eddi-1-268x358.jpg","tUauhMznXgVlKgvd5cWNAg==":"eddi-2-268x358.jpg","IdgZSAg69QWeZ00qBDWbvw==":"driver-license-card-122x122.png","BJYNbgeaVXLJKzOdY20tzw==":"preise%20f%C3%BChrer-436x249.png","AiDCpVYa5GHKy6XFpjFS3Q==":"preise%20f%C3%BChrer-792x453.png","eFqr2MR8F/kN0zdNpbXAkA==":"preise%20f%C3%BChrer-792x453.png","IU1TdWmA8XDRI2SuTSpqXw==":"preise-952x346.png","Ly+mdm63lVz6CqSX2vcU6g==":"background3.jpg","ihlkf69UyfSmhSyJ1Jvc6w==":"jumbotron.jpg","0OOE1Usrtktm437Z/qTMRQ==":"background2.jpg","HoeEF4HfT9nMa9Cg+v0y1w==":"02.jpg"}